pypiccolo/__init__.py
pypiccolo/__main__.py
pypiccolo/hello.py
pypiccolo/math.py
pypiccolo/math_utils.py
pypiccolo/sub_hello/__init__.py
pypiccolo/sub_hello/__main__.py
pypiccolo/sub_hello/hello.py
pypiccolo-0.0.1a1.dev1.dist-info/LICENSE
pypiccolo-0.0.1a1.dev1.dist-info/METADATA
pypiccolo-0.0.1a1.dev1.dist-info/WHEEL
pypiccolo-0.0.1a1.dev1.dist-info/top_level.txt
pypiccolo-0.0.1a1.dev1.dist-info/RECORD
