Metadata-Version: 2.2
Name: pypiccolo
Version: 0.0.1a1.dev1
Summary: Python wrapper of Piccolo.jl
Author-email: Gennadi Ryan <gennadiryan@gmail.com>
Maintainer-email: Gennadi Ryan <gennadiryan@gmail.com>, Jack Champagne <jchampag@andrew.cmu.edu>
License: MIT License
Keywords: quantum,physics,dynamics
Classifier: Development Status :: 3 - Alpha
Classifier: Intended Audience :: Science/Research
Classifier: Topic :: Scientific/Engineering :: Quantum Computing
Classifier: License :: OSI Approved :: MIT License
Classifier: Programming Language :: Python :: 3
Requires-Python: >=3.13
License-File: LICENSE
Requires-Dist: numpy>=2.2
Provides-Extra: tests
Requires-Dist: pytest>=8.3; extra == "tests"
